Workbook

Sheet Assumptions
A1: ParentProof - Revenue Model to Rs 1 Crore (26 weeks, Delhi NCR)
A2: Edit BLUE cells only. Yellow = key levers. Every number cites its basis in column D.
A4: PRICING
A5: Core plan (6 months) | B5: 999 | D5: Your live in-app price
A6: Annual plan | B6: 1799 | D6: Your live in-app price
A7: Plan mix - share choosing Core | B7: 0.8 | D7: Assumption: 6-mo commitment is the default choice at this price point; tune from real data monthly
A8: Blended D2C ARPU | B8: =B5*B7+B6*(1-B7) | D8: Mix-weighted price: Rs 1,159 at an 80/20 Core/Annual split
A9: B2B2C price per child (to you) | B9: 749 | D9: Bulk price via tuition/school partner; partner keeps ~Rs200-250 margin on Rs999 MRP
A11: FUNNEL
A12: Install -> first test (activation) | B12: 0.6 | D12: Assumption from pilot; product is 20-min first value. Measure weekly, this is lever #1
A13: Activation -> paid (early, W1-5) | B13: 0.08 | D13: Utility apps with exam anchor; starts low pre-proof
A14: Activation -> paid (peak, W22-26) | B14: 0.14 | D14: Pre-board panic season + accuracy receipts as proof; ramps in weekly sheet col F
A15: Share of D2C payers from PAID ads | B15: 0.45 | D15: Rest = referral, ground events, school opt-ins, partners, organic. WhatsApp-native product keeps this under half
A16: Paid CAC per payer (early) | B16: 650 | D16: CPI Rs40-120 benchmark (vmobify India 2026) x funnel math; conservative end
A17: Paid CAC per payer (late) | B17: 450 | D17: Improves with proof assets + seasonal intent; ramps in weekly sheet col H
A19: GOAL CHECK
A20: D2C payers (26-wk total) | B20: 7195 | D20: Sum of weekly targets (Weekly Model col E)
A21: B2B2C children (26-wk total) | B21: 2840 | D21: Via 16+ tuition/school partners by Jan
A22: D2C revenue | B22: =B20*B8 | D22: payers x blended ARPU
A23: B2B2C revenue | B23: =B21*B9 | D23: children x per-child price
A24: TOTAL REVENUE | B24: =B22+B23 | D24: Target: >= Rs 1,00,00,000
A25: Goal | B25: 10000000 | D25: Rs 1 crore
A26: Surplus / (gap) | B26: =B24-B25 | D26: Plan carries ~Rs 4.7L buffer
A28: Sources
A29: CPI benchmark: vmobify.com/blog/app-install-cost-india (EdTech K-12 India CPI Rs40-120, 2026). Exam dates: CBSE 2027 boards ~14 Feb-27 Mar (careers360/motion.ac.in). Festivals: Dussehra 20 Oct, Diwali 8 Nov 2026 (drikpanchang). All conversion rates are the author's assumptions - replace with your pilot data after Week 5.

Sheet Weekly Model
A1: Week | B1: Dates | C1: Phase | D1: D2C Payers | E1: B2B Children | F1: Activ->Paid % | G1: Installs Needed | H1: Paid CAC (Rs) | I1: Ad Spend (Rs) | J1: Other Mktg (Rs) | K1: D2C Revenue (Rs) | L1: B2B Revenue (Rs) | M1: Total Revenue (Rs) | N1: Cumulative (Rs) | O1: % of Rs1Cr
A2: 1 | B2: 28 Jul - 03 Aug | C2: P0 | D2: 0 | E2: 0 | F2: 0.08 | G2: =IF(F2=0,0,ROUND(D2/(Assumptions!$B$12*F2),0)) | H2: 650 | I2: =ROUND(D2*Assumptions!$B$15*H2,0) | J2: 3000 | K2: =D2*Assumptions!$B$8 | L2: =E2*Assumptions!$B$9 | M2: =K2+L2 | N2: =M2 | O2: =N2/Assumptions!$B$25
A3: 2 | B3: 04 Aug - 10 Aug | C3: P0 | D3: 5 | E3: 0 | F3: 0.08 | G3: =IF(F3=0,0,ROUND(D3/(Assumptions!$B$12*F3),0)) | H3: 650 | I3: =ROUND(D3*Assumptions!$B$15*H3,0) | J3: 4000 | K3: =D3*Assumptions!$B$8 | L3: =E3*Assumptions!$B$9 | M3: =K3+L3 | N3: =N2+M3 | O3: =N3/Assumptions!$B$25
A4: 3 | B4: 11 Aug - 17 Aug | C4: P1 | D4: 15 | E4: 0 | F4: 0.08 | G4: =IF(F4=0,0,ROUND(D4/(Assumptions!$B$12*F4),0)) | H4: 650 | I4: =ROUND(D4*Assumptions!$B$15*H4,0) | J4: 6000 | K4: =D4*Assumptions!$B$8 | L4: =E4*Assumptions!$B$9 | M4: =K4+L4 | N4: =N3+M4 | O4: =N4/Assumptions!$B$25
A5: 4 | B5: 18 Aug - 24 Aug | C5: P1 | D5: 25 | E5: 0 | F5: 0.08 | G5: =IF(F5=0,0,ROUND(D5/(Assumptions!$B$12*F5),0)) | H5: 650 | I5: =ROUND(D5*Assumptions!$B$15*H5,0) | J5: 8000 | K5: =D5*Assumptions!$B$8 | L5: =E5*Assumptions!$B$9 | M5: =K5+L5 | N5: =N4+M5 | O5: =N5/Assumptions!$B$25
A6: 5 | B6: 25 Aug - 31 Aug | C6: P1 | D6: 40 | E6: 0 | F6: 0.08 | G6: =IF(F6=0,0,ROUND(D6/(Assumptions!$B$12*F6),0)) | H6: 650 | I6: =ROUND(D6*Assumptions!$B$15*H6,0) | J6: 8000 | K6: =D6*Assumptions!$B$8 | L6: =E6*Assumptions!$B$9 | M6: =K6+L6 | N6: =N5+M6 | O6: =N6/Assumptions!$B$25
A7: 6 | B7: 01 Sep - 07 Sep | C7: P2 | D7: 60 | E7: 40 | F7: 0.09 | G7: =IF(F7=0,0,ROUND(D7/(Assumptions!$B$12*F7),0)) | H7: 600 | I7: =ROUND(D7*Assumptions!$B$15*H7,0) | J7: 9000 | K7: =D7*Assumptions!$B$8 | L7: =E7*Assumptions!$B$9 | M7: =K7+L7 | N7: =N6+M7 | O7: =N7/Assumptions!$B$25
A8: 7 | B8: 08 Sep - 14 Sep | C8: P2 | D8: 80 | E8: 40 | F8: 0.09 | G8: =IF(F8=0,0,ROUND(D8/(Assumptions!$B$12*F8),0)) | H8: 600 | I8: =ROUND(D8*Assumptions!$B$15*H8,0) | J8: 12000 | K8: =D8*Assumptions!$B$8 | L8: =E8*Assumptions!$B$9 | M8: =K8+L8 | N8: =N7+M8 | O8: =N8/Assumptions!$B$25
A9: 8 | B9: 15 Sep - 21 Sep | C9: P2 | D9: 100 | E9: 60 | F9: 0.09 | G9: =IF(F9=0,0,ROUND(D9/(Assumptions!$B$12*F9),0)) | H9: 600 | I9: =ROUND(D9*Assumptions!$B$15*H9,0) | J9: 12000 | K9: =D9*Assumptions!$B$8 | L9: =E9*Assumptions!$B$9 | M9: =K9+L9 | N9: =N8+M9 | O9: =N9/Assumptions!$B$25
A10: 9 | B10: 22 Sep - 28 Sep | C10: P2 | D10: 130 | E10: 60 | F10: 0.09 | G10: =IF(F10=0,0,ROUND(D10/(Assumptions!$B$12*F10),0)) | H10: 600 | I10: =ROUND(D10*Assumptions!$B$15*H10,0) | J10: 14000 | K10: =D10*Assumptions!$B$8 | L10: =E10*Assumptions!$B$9 | M10: =K10+L10 | N10: =N9+M10 | O10: =N10/Assumptions!$B$25
A11: 10 | B11: 29 Sep - 05 Oct | C11: P3 | D11: 160 | E11: 80 | F11: 0.1 | G11: =IF(F11=0,0,ROUND(D11/(Assumptions!$B$12*F11),0)) | H11: 550 | I11: =ROUND(D11*Assumptions!$B$15*H11,0) | J11: 12000 | K11: =D11*Assumptions!$B$8 | L11: =E11*Assumptions!$B$9 | M11: =K11+L11 | N11: =N10+M11 | O11: =N11/Assumptions!$B$25
A12: 11 | B12: 06 Oct - 12 Oct | C12: P3 | D12: 190 | E12: 80 | F12: 0.1 | G12: =IF(F12=0,0,ROUND(D12/(Assumptions!$B$12*F12),0)) | H12: 550 | I12: =ROUND(D12*Assumptions!$B$15*H12,0) | J12: 14000 | K12: =D12*Assumptions!$B$8 | L12: =E12*Assumptions!$B$9 | M12: =K12+L12 | N12: =N11+M12 | O12: =N12/Assumptions!$B$25
A13: 12 | B13: 13 Oct - 19 Oct | C13: P3 | D13: 220 | E13: 100 | F13: 0.1 | G13: =IF(F13=0,0,ROUND(D13/(Assumptions!$B$12*F13),0)) | H13: 550 | I13: =ROUND(D13*Assumptions!$B$15*H13,0) | J13: 16000 | K13: =D13*Assumptions!$B$8 | L13: =E13*Assumptions!$B$9 | M13: =K13+L13 | N13: =N12+M13 | O13: =N13/Assumptions!$B$25
A14: 13 | B14: 20 Oct - 26 Oct | C14: P3 | D14: 250 | E14: 100 | F14: 0.1 | G14: =IF(F14=0,0,ROUND(D14/(Assumptions!$B$12*F14),0)) | H14: 550 | I14: =ROUND(D14*Assumptions!$B$15*H14,0) | J14: 16000 | K14: =D14*Assumptions!$B$8 | L14: =E14*Assumptions!$B$9 | M14: =K14+L14 | N14: =N13+M14 | O14: =N14/Assumptions!$B$25
... A27: 26 | B27: 19 Jan - 25 Jan | C27: P6 | D27: 680 | E27: 240 | F27: 0.14 | G27: =IF(F27=0,0,ROUND(D27/(Assumptions!$B$12*F27),0)) | H27: 450 | I27: =ROUND(D27*Assumptions!$B$15*H27,0) | J27: 18000 | K27: =D27*Assumptions!$B$8 | L27: =E27*Assumptions!$B$9 | M27: =K27+L27 | N27: =N26+M27 | O27: =N27/Assumptions!$B$25
C28: TOTAL | D28: =SUM(D2:D27) | E28: =SUM(E2:E27) | G28: =SUM(G2:G27) | I28: =SUM(I2:I27) | J28: =SUM(J2:J27) | K28: =SUM(K2:K27) | L28: =SUM(L2:L27) | M28: =SUM(M2:M27)

Sheet Budget
A1: 26-Week Marketing Budget (Base scenario)
A3: Line item | B3: Amount (Rs) | C3: Basis
A4: Meta/Google ads (performance) | B4: ='Weekly Model'!I28 | C4: Sum of weekly ad spend (payers x paid-share x CAC)
A5: Ground events & society melas (26 wks) | B5: 78000 | C5: ~35 events/booths x Rs1,500-4,000 avg (tables, standees, mela fees)
A6: Micro-influencers (2 waves, ~15 creators) | B6: 60000 | C6: Rs2-5k per reel + free Annuals
A7: Referral rewards & contests | B7: 90000 | C7: 1-mo extensions + 2 contests x Rs15k prizes + 3-cousins discounts
A8: Content production (design tools, editing) | B8: 40000 | C8: Canva Pro, CapCut, occasional freelance editor
A9: School/tuition BD (travel, printed one-pagers, demo kits) | B9: 50000 | C9: ~80 field visits + workshop materials
A10: Webinars & tools (Zoom, WA Business API, CRM sheet tools) | B10: 30000 | C10: 6 webinars + messaging tools
A11: PR (press kit, wire, misc) | B11: 25000 | C11: DIY-first; no agency
A12: Field interns (1 from Oct, 2 from Dec) | B12: 108000 | C12: Rs12k/month x intern-months (Oct-Jan)
A13: Contingency (10%) | B13: =ROUND(SUM(B4:B12)*0.1,0) | C13: Buffer
A14: TOTAL BUDGET | B14: =SUM(B4:B13)
A16: Budget as % of revenue | B16: =B14/Assumptions!B24 | C16: Healthy D2C subscription range is 25-35% in year 1
A17: Blended CAC (all payers, all spend) | B17: =B14/(Assumptions!B20+Assumptions!B21)

Sheet Scenarios & Levers
A1: Three scenarios (multipliers on Base weekly targets)
B3: Lean (x0.6) | C3: Base (x1.0) | D3: Aggressive (x1.3)
A4: Multiplier | B4: 0.6 | C4: 1 | D4: 1.3
A5: D2C payers | B5: =B4*Assumptions!$B$20 | C5: =C4*Assumptions!$B$20 | D5: =D4*Assumptions!$B$20
A6: B2B children | B6: =B4*Assumptions!$B$21 | C6: =C4*Assumptions!$B$21 | D6: =D4*Assumptions!$B$21
A7: Revenue | B7: =B5*Assumptions!$B$8+B6*Assumptions!$B$9 | C7: =C5*Assumptions!$B$8+C6*Assumptions!$B$9 | D7: =D5*Assumptions!$B$8+D6*Assumptions!$B$9
A8: vs Rs 1 Cr | B8: =B7/Assumptions!$B$25 | C8: =C7/Assumptions!$B$25 | D8: =D7/Assumptions!$B$25
A10: Read: even Lean lands ~Rs 63L - the plan degrades gracefully. Aggressive needs 2 extra field hires + Rs45L budget.
A12: CONTINGENCY LEVERS - pull in W24 gap-analysis if cumulative < 80% of target
A13: 1. B2B bulk deals: one 500-child school deal at Rs599/child = Rs3L in one contract. Aim: 2 such deals via the school workshop pipeline.
A14: 2. Price test: 3-month Rs599 plan for fence-sitters (protects Rs999 anchor; adds an entry rung before boards).
A15: 3. Referral double-down: double contest prize, add instant Rs100 UPI per paying referral (CAC still < Rs450).
A16: 4. Geography: open Jaipur/Chandigarh/Lucknow via pure WhatsApp + partner playbook (no ground ops) - NCR playbook is remote-replicable.
A17: 5. Corporate: pitch 5 NCR companies' HR for 'employee kids audit' as a benefits perk (bulk Annual).
A18: 6. The Rs99 single-audit tier (tested W20): if trial->Core >= 25%, make it the default ad CTA - drops effective CAC sharply.
